odoo/addons/partner_mobile_unique/README.rst
odoo/addons/partner_mobile_unique/__init__.py
odoo/addons/partner_mobile_unique/__manifest__.py
odoo/addons/partner_mobile_unique/i18n/es.po
odoo/addons/partner_mobile_unique/i18n/it.po
odoo/addons/partner_mobile_unique/i18n/partner_mobile_unique.pot
odoo/addons/partner_mobile_unique/models/__init__.py
odoo/addons/partner_mobile_unique/models/res_company.py
odoo/addons/partner_mobile_unique/models/res_config_settings.py
odoo/addons/partner_mobile_unique/models/res_partner.py
odoo/addons/partner_mobile_unique/readme/CONFIGURE.rst
odoo/addons/partner_mobile_unique/readme/CONTRIBUTORS.rst
odoo/addons/partner_mobile_unique/readme/DESCRIPTION.rst
odoo/addons/partner_mobile_unique/readme/USAGE.rst
odoo/addons/partner_mobile_unique/static/description/icon.png
odoo/addons/partner_mobile_unique/static/description/index.html
odoo/addons/partner_mobile_unique/static/description/partner_duplicate_error.png
odoo/addons/partner_mobile_unique/tests/__init__.py
odoo/addons/partner_mobile_unique/tests/test_mobile_check_unique.py
odoo/addons/partner_mobile_unique/views/res_config_settings_view.xml
odoo14_addon_partner_mobile_unique-14.0.1.0.1.dev8.dist-info/METADATA
odoo14_addon_partner_mobile_unique-14.0.1.0.1.dev8.dist-info/WHEEL
odoo14_addon_partner_mobile_unique-14.0.1.0.1.dev8.dist-info/top_level.txt
odoo14_addon_partner_mobile_unique-14.0.1.0.1.dev8.dist-info/RECORD
